designs_n_tb/10_lift/timer.v
module timer(
    //system input
    input clk,
    //module input
    input [31:0] current_state,
    input [31:0] nfloor,
    input [31:0] pfloor,

    output reached);
/*
This design module is monitors the time of moving the lift up or down. 
It takes as input 
1. clock, 
2. present state of lift
3. present floor
4. next floor

and generates binary output
1. reached = 0 for not reached and = 1 for reached

This program is implemented in two always block
1. with continuous block
2. with positive clock edge
*/
parameter STATE_DOOR_OPEN  = 1;
parameter STATE_DOOR_CLOSE = 2;
parameter STATE_READY      = 3;
parameter STATE_MOVE_UP    = 4;
parameter STATE_MOVE_DOWN  = 5;

reg reached;
reg flag;
integer counter;
integer targetcount;
integer speed = 1;// number of clock cycles for one floor travel
initial flag = 1;

always @(posedge clk)
    begin
        if ((current_state == STATE_MOVE_DOWN) | (current_state == STATE_MOVE_UP))
            begin
            if (flag == 1)
                begin
                    counter  = 1;
                    flag     = 0;
                    reached  = 0;
                    if (pfloor > nfloor)      targetcount = (pfloor - nfloor) * speed;
                    else if (pfloor < nfloor) targetcount = (nfloor - pfloor) * speed;
                end
            
            else if (flag == 0) 
                begin
                    counter = counter + 1;
                    if (counter == targetcount) 
                        begin
                        reached = 1;
                        flag    = 1;
                        counter = 1;
                        #(speed+4)
                        reached = 0;
                        end
                end
            end        
    end


/*
always 
    begin
        if ((current_state == STATE_MOVE_DOWN) | (current_state == STATE_MOVE_UP))
            begin
                if (nfloor == pfloor)
                    reached = 1;
                else
                    reached = 0;
            end
        else
            reached = 0;
    end
*/
endmodule

designs_n_tb/10_lift/controller.v
module controller(
    // input from outside world
    input clk,
    // input floor request - Eleven floors
    input in0, in1, in2, in3, in4, in5, in6, in7, in8, in9, in10, 
    // input sensor signals
    input in_door_obstacle,
    // input from inside lift
    input in_door_open,
    input in_door_close,
    // input from timer
    input reached,

    // operation states
    output out_up_direction,
    output out_down_direction,
    output out_door_opening,
    output out_door_closing,
    output out_ready,

    // output to timer
    output integer current_state,
    output integer nfloor,
    output integer pfloor);
/*
This design module has two components
1. state transitions
2. scheduling of lift floor requests

*/

/*
reg out_door_opening;
reg out_door_closing;
reg out_up_direction;
reg out_down_direction;
reg out_ready;

reg current_state;*/
//reg integer pfloor;
//reg integer current_state;
//reg integer nfloor;
reg dir;// dir = 1 up direction, dir = 0 for down direction

parameter STATE_DOOR_OPEN  = 1;
parameter STATE_DOOR_CLOSE = 2;
parameter STATE_READY      = 3;
parameter STATE_MOVE_UP    = 4;
parameter STATE_MOVE_DOWN  = 5;

initial begin
dir           = 1;
current_state = STATE_READY;
pfloor        = 0;
nfloor        = 0;
end

// state transition (current_state)

always @(posedge clk)
    begin
    case (current_state)
        STATE_DOOR_OPEN:
            begin
            if  (in_door_obstacle | in_door_open)
                current_state = STATE_DOOR_OPEN;
            else 
                current_state = STATE_DOOR_CLOSE;
            end

        STATE_DOOR_CLOSE:
            begin
            if  (in_door_open)
                current_state = STATE_DOOR_OPEN;
            else
                current_state = STATE_READY;
            end

        STATE_READY:
            begin
            if      (in_door_open)
                    current_state = STATE_DOOR_OPEN;
            else if (pfloor < nfloor)
                    current_state = STATE_MOVE_UP;
            else if (pfloor > nfloor)
                    current_state = STATE_MOVE_DOWN;        
            else if (pfloor == nfloor)
                    current_state = STATE_READY; 
            else
                    current_state = STATE_READY;
            end  

        STATE_MOVE_UP:
            begin
            if (reached) 
                begin
                current_state = STATE_DOOR_OPEN;
                pfloor = nfloor;
                /*case (pfloor)
                    0:  in0  = 1'b0;
                    1:  in1  = 1'b0;
                    2:  in2  = 1'b0;
                    3:  in3  = 1'b0;
                    4:  in4  = 1'b0;
                    5:  in5  = 1'b0;
                    6:  in6  = 1'b0;
                    7:  in7  = 1'b0;
                    8:  in8  = 1'b0;
                    9:  in9  = 1'b0;
                    10: in10 = 1'b0;
                endcase*/
                end
            else
                current_state = STATE_MOVE_UP;
            end

        STATE_MOVE_DOWN:
            begin
            if (reached)
                begin
                current_state = STATE_DOOR_OPEN;
                pfloor = nfloor;
                /*case (pfloor)
                    0:  in0  = 1'b0;
                    1:  in1  = 1'b0;
                    2:  in2  = 1'b0;
                    3:  in3  = 1'b0;
                    4:  in4  = 1'b0;
                    5:  in5  = 1'b0;
                    6:  in6  = 1'b0;
                    7:  in7  = 1'b0;
                    8:  in8  = 1'b0;
                    9:  in9  = 1'b0;
                    10: in10 = 1'b0;
                endcase*/
                end
            else 
                current_state = STATE_MOVE_DOWN;
            end

        default: current_state = STATE_READY;
    endcase
end

// next floor decision making algorithm
always @(posedge clk)
    begin
    // scanning input requests for the all the ten floors
/*    if (in0)  in0  = 1;
    if (in1)  in1  = 1;
    if (in2)  in2  = 1;
    if (in3)  in3  = 1;
    if (in4)  in4  = 1;
    if (in5)  in5  = 1;
    if (in6)  in6  = 1;
    if (in7)  in7  = 1;
    if (in8)  in8  = 1;
    if (in9)  in9  = 1;
    if (in10) in10 = 1;
*/
    if (dir)
        begin
            case (pfloor)
            0:  begin
                     if (in1)  nfloor = 1;
                else if (in2)  nfloor = 2;
                else if (in3)  nfloor = 3;
                else if (in4)  nfloor = 4;
                else if (in5)  nfloor = 5;
                else if (in6)  nfloor = 6;
                else if (in7)  nfloor = 7;
                else if (in8)  nfloor = 8;
                else if (in9)  nfloor = 9;
                else if (in10) nfloor = 10;
                else           nfloor = pfloor;
                end
            1:  begin
                     if (in2)  nfloor = 2;
                else if (in3)  nfloor = 3;
                else if (in4)  nfloor = 4;
                else if (in5)  nfloor = 5;
                else if (in6)  nfloor = 6;
                else if (in7)  nfloor = 7;
                else if (in8)  nfloor = 8;
                else if (in9)  nfloor = 9;
                else if (in10) nfloor = 10;
                else if (in0)  dir = 0;
                else           nfloor = pfloor;
                end
            2:  begin
                     if (in3)  nfloor = 3;
                else if (in4)  nfloor = 4;
                else if (in5)  nfloor = 5;
                else if (in6)  nfloor = 6;
                else if (in7)  nfloor = 7;
                else if (in8)  nfloor = 8;
                else if (in9)  nfloor = 9;
                else if (in10) nfloor = 10;
                else if (in0 | in1) dir = 0;
                else           nfloor = pfloor;
                end
            3:  begin
                     if (in4)  nfloor = 4;
                else if (in5)  nfloor = 5;
                else if (in6)  nfloor = 6;
                else if (in7)  nfloor = 7;
                else if (in8)  nfloor = 8;
                else if (in9)  nfloor = 9;
                else if (in10) nfloor = 10;
                else if (in0 | in1 | in2) dir = 0;
                else           nfloor = pfloor;
                end
            4:  begin
                     if (in5)  nfloor = 5;
                else if (in6)  nfloor = 6;
                else if (in7)  nfloor = 7;
                else if (in8)  nfloor = 8;
                else if (in9)  nfloor = 9;
                else if (in10) nfloor = 10;
                else if (in0 | in1 | in2 | in3) dir = 0;
                else           nfloor = pfloor;
                end
            5:  begin
                     if (in6)  nfloor = 6;
                else if (in7)  nfloor = 7;
                else if (in8)  nfloor = 8;
                else if (in9)  nfloor = 9;
                else if (in10) nfloor = 10;
                else if (in0 | in1 | in2 | in3 | in4) dir = 0;
                else           nfloor = pfloor;
                end
            6:  begin
                     if (in7)  nfloor = 7;
                else if (in8)  nfloor = 8;
                else if (in9)  nfloor = 9;
                else if (in10) nfloor = 10;
                else if (in0 | in1 | in2 | in3 | in4 | in5) dir = 0;
                else           nfloor = pfloor;
                end
            7:  begin
                     if (in8)  nfloor = 8;
                else if (in9)  nfloor = 9;
                else if (in10) nfloor = 10;
                else if (in0 | in1 | in2 | in3 | in4 | in5 | in6) dir = 0;
                else           nfloor = pfloor;
                end
            8:  begin
                     if (in9)  nfloor = 9;
                else if (in10) nfloor = 10;
                else if (in0 | in1 | in2 | in3 | in4 | in5 | in6 | in7) dir = 0;
                else           nfloor = pfloor;
                end
            9:  begin
                     if (in10) nfloor = 10;
                else if (in0 | in1 | in2 | in3 | in4 | in5 | in6 | in7 | in8) dir = 0;
                else           nfloor = pfloor;
                end
            10:      dir = 0;
            endcase
        end
    else if (~dir)
        begin
            case (pfloor)
            0: dir = 1;
            
            1:  begin
                     if (in0) nfloor = 0;
                else if (in2 | in3 | in4 | in5 | in6 | in7 | in8 | in9 | in10 ) dir = 1;
                else          nfloor = pfloor;
                end
            
            2:  begin
                     if (in1) nfloor = 1;
                else if (in0) nfloor = 0;
                else if (in3 | in4 | in5 | in6 | in7 | in8 | in9 | in10 ) dir = 1;
                else          nfloor = pfloor;
                end
            
            3:  begin
                     if (in2) nfloor = 2;     
                else if (in1) nfloor = 1;
                else if (in0) nfloor = 0;
                else if (in4 | in5 | in6 | in7 | in8 | in9 | in10 ) dir = 1;
                else          nfloor = pfloor;
                end
            
            4:  begin
                     if (in3) nfloor = 3;
                else if (in2) nfloor = 2;     
                else if (in1) nfloor = 1;
                else if (in0) nfloor = 0;
                else if (in5 | in6 | in7 | in8 | in9 | in10 ) dir = 1;
                else          nfloor = pfloor;
                end

            5:  begin
                     if (in4) nfloor = 4;
                else if (in3) nfloor = 3;
                else if (in2) nfloor = 2;     
                else if (in1) nfloor = 1;
                else if (in0) nfloor = 0;
                else if (in6 | in7 | in8 | in9 | in10 ) dir = 1;
                else          nfloor = pfloor;
                end

            6:  begin
                     if (in5) nfloor = 5;
                else if (in4) nfloor = 4;
                else if (in3) nfloor = 3;
                else if (in2) nfloor = 2;     
                else if (in1) nfloor = 1;
                else if (in0) nfloor = 0;
                else if (in7 | in8 | in9 | in10 ) dir = 1;
                else          nfloor = pfloor;
                end
            
            7:  begin
                     if (in6) nfloor = 6;
                else if (in5) nfloor = 5;
                else if (in4) nfloor = 4;
                else if (in3) nfloor = 3;
                else if (in2) nfloor = 2;     
                else if (in1) nfloor = 1;
                else if (in0) nfloor = 0;
                else if (in8 | in9 | in10 ) dir = 1;
                else          nfloor = pfloor;
                end

            8:  begin
                     if (in7) nfloor = 7;
                else if (in6) nfloor = 6;
                else if (in5) nfloor = 5;
                else if (in4) nfloor = 4;
                else if (in3) nfloor = 3;
                else if (in2) nfloor = 2;     
                else if (in1) nfloor = 1;
                else if (in0) nfloor = 0;
                else if (in9 | in10) dir = 1;
                else          nfloor = pfloor;
                end

            9:  begin
                     if (in8) nfloor = 8;
                else if (in7) nfloor = 7;
                else if (in6) nfloor = 6;
                else if (in5) nfloor = 5;
                else if (in4) nfloor = 4;
                else if (in3) nfloor = 3;
                else if (in2) nfloor = 2;     
                else if (in1) nfloor = 1;
                else if (in0) nfloor = 0;
                else if (in10) dir   = 1;
                else          nfloor = pfloor;
                end

            10: begin
                     if (in9) nfloor = 9;
                else if (in8) nfloor = 8;
                else if (in7) nfloor = 7;
                else if (in6) nfloor = 6;
                else if (in5) nfloor = 5;
                else if (in4) nfloor = 4;
                else if (in3) nfloor = 3;
                else if (in2) nfloor = 2;     
                else if (in1) nfloor = 1;
                else if (in0) nfloor = 0;
                else          nfloor = pfloor;
            end
            endcase

        end
end

// output signals
//assign current_state             = current_state;
assign out_door_closing   = (current_state == STATE_DOOR_CLOSE)?1:0;
assign out_door_opening   = (current_state == STATE_DOOR_OPEN)?1:0;
assign out_down_direction = (current_state == STATE_MOVE_DOWN)?1:0;
assign out_up_direction   = (current_state == STATE_MOVE_UP)?1:0;
assign out_ready          = (current_state == STATE_READY)?1:0;

endmodule

designs_n_tb/10_lift/lift_controller.v
`include "controller.v"
`include "timer.v"
module Microcontroller_lift(
    input clk,
    input in0,in1,in2,in3,in4,in5,in6,in7,in8,in9,in10,
    input in_door_obstacle,
    input in_door_open,
    input in_door_close,

    output out_up_direction,
    output out_down_direction,
    output out_door_opening,
    output out_door_closing,
    output out_ready);

wire reached;
wire integer current_state;
wire integer nfloor;
wire integer pfloor;

controller cu(
    //input
    .clk(clk),
    .in0(in0), .in1(in1), .in2(in2), .in3(in3),
    .in4(in4), .in5(in5), .in6(in6), .in7(in7),
    .in8(in8), .in9(in9), .in10(in10),

    .in_door_obstacle(in_door_obstacle),
    .in_door_open(in_door_open),
    .in_door_close(in_door_close),

    .reached(reached),
    .out_up_direction(out_up_direction),
    .out_down_direction(out_down_direction),
    .out_door_opening(out_door_opening),
    .out_door_closing(out_door_closing),
    .out_ready,
    .current_state(current_state),
    .nfloor(nfloor),
    .pfloor(pfloor)
);

timer ti(
    //input
    .clk(clk),
    .current_state(current_state),
    .nfloor(nfloor),
    .pfloor(pfloor),
    //output
    .reached(reached)
);

endmodule

designs_n_tb/10_lift/lift_controller_tb.v
`include "lift_controller.v"
module lift_controller_tb();

reg clk;
reg in0,in1,in2,in3,in4,in5,in6,in7,in8,in9,in10;
reg in_door_obstacle;
reg in_door_open;
reg in_door_close;

wire out_up_direction;
wire out_down_direction;
wire out_door_opening;
wire out_door_closing;
wire out_ready;


initial begin
    clk = 1'b0;

    in0 = 1'b0;
    in1 = 1'b0;
    in2 = 1'b0;
    in3 = 1'b0;
    in4 = 1'b0;
    in5 = 1'b0;
    in6 = 1'b0;
    in7 = 1'b0;
    in8 = 1'b0;
    in9 = 1'b0;
    in10 = 1'b0;

    in_door_obstacle = 1'b0;
    in_door_open = 1'b0;
    in_door_close = 1'b0;
end

initial #200 $finish;
always #10 clk = ~clk;


Microcontroller_lift ucl(  
    clk,
    in0,in1,in2,in3,in4,in5,in6,in7,in8,in9,in10,
    in_door_obstacle,
    in_door_open,
    in_door_close,
    out_up_direction,
    out_down_direction,
    out_door_opening,
    out_door_closing,
    out_ready);

initial begin
    $dumpfile("lift_controller.vcd");
    $dumpvars;
end
endmodule

designs_n_tb/10_lift/lift_controller.vcd
$date
	Fri Jul 21 17:18:00 2023
$end
$version
	Icarus Verilog
$end
$timescale
	1s
$end
$scope module lift_controller_tb $end
$var wire 1 ! out_up_direction $end
$var wire 1 " out_ready $end
$var wire 1 # out_down_direction $end
$var wire 1 $ out_door_opening $end
$var wire 1 % out_door_closing $end
$var reg 1 & clk $end
$var reg 1 ' in0 $end
$var reg 1 ( in1 $end
$var reg 1 ) in10 $end
$var reg 1 * in2 $end
$var reg 1 + in3 $end
$var reg 1 , in4 $end
$var reg 1 - in5 $end
$var reg 1 . in6 $end
$var reg 1 / in7 $end
$var reg 1 0 in8 $end
$var reg 1 1 in9 $end
$var reg 1 2 in_door_close $end
$var reg 1 3 in_door_obstacle $end
$var reg 1 4 in_door_open $end
$scope module ucl $end
$var wire 1 & clk $end
$var wire 1 ' in0 $end
$var wire 1 ( in1 $end
$var wire 1 ) in10 $end
$var wire 1 * in2 $end
$var wire 1 + in3 $end
$var wire 1 , in4 $end
$var wire 1 - in5 $end
$var wire 1 . in6 $end
$var wire 1 / in7 $end
$var wire 1 0 in8 $end
$var wire 1 1 in9 $end
$var wire 1 2 in_door_close $end
$var wire 1 3 in_door_obstacle $end
$var wire 1 4 in_door_open $end
$var wire 1 5 reached $end
$var wire 32 6 pfloor [31:0] $end
$var wire 1 ! out_up_direction $end
$var wire 1 " out_ready $end
$var wire 1 # out_down_direction $end
$var wire 1 $ out_door_opening $end
$var wire 1 % out_door_closing $end
$var wire 32 7 nfloor [31:0] $end
$var wire 32 8 current_state [31:0] $end
$scope module cu $end
$var wire 1 & clk $end
$var wire 1 ' in0 $end
$var wire 1 ( in1 $end
$var wire 1 ) in10 $end
$var wire 1 * in2 $end
$var wire 1 + in3 $end
$var wire 1 , in4 $end
$var wire 1 - in5 $end
$var wire 1 . in6 $end
$var wire 1 / in7 $end
$var wire 1 0 in8 $end
$var wire 1 1 in9 $end
$var wire 1 2 in_door_close $end
$var wire 1 3 in_door_obstacle $end
$var wire 1 4 in_door_open $end
$var wire 1 5 reached $end
$var wire 1 ! out_up_direction $end
$var wire 1 " out_ready $end
$var wire 1 # out_down_direction $end
$var wire 1 $ out_door_opening $end
$var wire 1 % out_door_closing $end
$var reg 32 9 current_state [31:0] $end
$var reg 1 : dir $end
$var reg 32 ; nfloor [31:0] $end
$var reg 32 < pfloor [31:0] $end
$upscope $end
$scope module ti $end
$var wire 1 & clk $end
$var wire 32 = current_state [31:0] $end
$var wire 32 > nfloor [31:0] $end
$var wire 32 ? pfloor [31:0] $end
$var reg 1 @ flag $end
$var reg 1 5 reached $end
$var integer 32 A counter [31:0] $end
$var integer 32 B speed [31:0] $end
$var integer 32 C targetcount [31:0] $end
$upscope $end
$upscope $end
$upscope $end
$enddefinitions $end
#0
$dumpvars
bx C
b1 B
bx A
1@
b0 ?
b0 >
b11 =
b0 <
b0 ;
1:
b11 9
b11 8
b0 7
b0 6
x5
04
03
02
01
00
0/
0.
0-
0,
0+
0*
0)
0(
0'
0&
0%
0$
0#
1"
0!
$end
#10
1&
#20
0&
1,
#30
b100 7
b100 ;
b100 >
1&
#40
0&
#50
1!
0"
b100 8
b100 9
b100 =
1&
#60
0&
#70
b100 C
05
0@
b1 A
1&
#80
0&
#90
b10 A
1&
#100
0&
#110
b11 A
1&
#120
0&
#130
1$
0!
b100 6
b100 <
b100 ?
b1 8
b1 9
b1 =
1@
15
b1 A
1&
#135
05
#140
0&
#150
1%
0$
b10 8
b10 9
b10 =
1&
#160
0&
#170
0%
1"
b11 8
b11 9
b11 =
1&
#180
0&
10
#190
b1000 7
b1000 ;
b1000 >
1&
#200
0&
#210
1!
0"
0@
b100 8
b100 9
b100 =
1&
#220
0&
#230
b10 A
1&
1'
#240
0&
#250
b11 A
1&
#260
0&
#270
1$
0!
0:
b1000 6
b1000 <
b1000 ?
b1 8
b1 9
b1 =
1@
15
b1 A
1&
#275
05
#280
0&
#290
1%
0$
b10 8
b10 9
b10 =
b100 7
b100 ;
b100 >
1&
#300
0&
#310
0%
1"
b11 8
b11 9
b11 =
1&
#320
0&
#330
1#
0"
b101 8
b101 9
b101 =
1&
#340
0&
#350
0@
1&
#360
0&
#370
b10 A
1&
#380
0&
#390
b11 A
1&
#400
0&
#410
1$
0#
b100 6
b100 <
b100 ?
b1 8
b1 9
b1 =
1@
15
b1 A
1&
#415
05
#420
0&
#430
1%
0$
b0 7
b0 ;
b0 >
b10 8
b10 9
b10 =
1&
#440
0&
#450
0%
1"
b11 8
b11 9
b11 =
1&
#460
0&
#470
1#
0"
b101 8
b101 9
b101 =
1&
#480
0&
#490
0@
1&
#500
0&
#510
b10 A
1&
#520
0&
#530
b11 A
1&
#540
0&
#550
1$
0#
1:
b0 6
b0 <
b0 ?
b1 8
b1 9
b1 =
1@
15
b1 A
1&
#555
05
#560
0&
#570
1%
0$
b10 8
b10 9
b10 =
b100 7
b100 ;
b100 >
1&
#580
0&
#590
0%
1"
b11 8
b11 9
b11 =
1&
