designs_n_tb/9_washing_machine_controller/controller.v
// ref: https://github.com/yasnakateb/WMController
module Controller(
    clock,
    input1,
    input2,
    input3,
    input4,
    input5,
    input6,
    sig_Lid_Closed,
    sig_Coin,
    sig_Cancel,
    sig_Time_Out,
    sig_Out_Of_Balance,
    sig_Motor_Failure,
    sig_Full,
    sig_Temperature,
    sig_Wash_Completed,
    sig_Rinse_Completed,
    sig_Spin_Completed,
    start,
    ready,
    fill_Water_Operation,
    heat_Water_Operation,
    wash_Operation,
    rinse_Operation,
    spin_Operation,
    fault,
    coin_Return,
    water_Intake,
    fault_Cleared,
    state
    );
    
    input clock;
    input input1,input2,input3,input4,input5,input6;
    input sig_Lid_Closed;
    input sig_Coin;

    input sig_Cancel;
    input sig_Time_Out;
    input sig_Out_Of_Balance;
    input sig_Motor_Failure;

    input sig_Full;
    input sig_Temperature;
    input sig_Wash_Completed;
    input sig_Rinse_Completed;
    input sig_Spin_Completed;

    output start;
    output ready;
    output fill_Water_Operation;
    output heat_Water_Operation;
    output wash_Operation;
    output rinse_Operation;
    output spin_Operation;
    output fault;
    output coin_Return;
    output water_Intake;
    output fault_Cleared;
    output [2:0] state;

    parameter STATE_START = 3'd0 ;
    parameter STATE_READY = 3'd1;
    parameter STATE_FILL_WATER = 3'd2;
    parameter STATE_HEAT_WATER = 3'd3;
    parameter STATE_WASH = 3'd4;
    parameter STATE_RINSE = 3'd5;
    parameter STATE_SPIN = 3'd6;
    parameter STATE_FAULT = 3'd7;

    reg state = STATE_START;
    reg [2:0] next_State;

    always @(posedge  clock) begin
        state = next_State;
    end

    always @(posedge clock) begin
    if (input1) begin
        case (state)
            STATE_START: begin
                if (sig_Coin == 1)
                    next_State = STATE_READY;

                else 
                    next_State = STATE_START;
            end
            STATE_READY: begin
                if (sig_Lid_Closed == 1)
                    next_State = STATE_FILL_WATER;

                else if (sig_Cancel == 1)
                    next_State = STATE_START;
            end
            STATE_FILL_WATER: begin
                if (sig_Cancel == 1)
                    next_State = STATE_START;

                else if (sig_Full == 1)
                    next_State = STATE_HEAT_WATER;
                
                else if (sig_Time_Out == 1)
                    next_State = STATE_FAULT;
                
                else 
                    next_State = STATE_FILL_WATER;
            end
            STATE_HEAT_WATER: begin
                if (sig_Cancel == 1)
                    next_State = STATE_START;

                else if (sig_Temperature == 1) 
                    next_State = STATE_WASH;
                    
                else if (sig_Time_Out == 1) 
                    next_State = STATE_FAULT;
                
                else 
                    next_State = STATE_HEAT_WATER;
            end
            STATE_WASH: begin
                if (sig_Cancel == 1)
                    next_State = STATE_START;

                else if (sig_Wash_Completed == 1) 
                    next_State = STATE_RINSE;
                    
                else if (sig_Out_Of_Balance == 1)
                    next_State = STATE_FAULT;
        
                else 
                    next_State = STATE_WASH;
            end
            STATE_RINSE: begin
                if (sig_Cancel == 1)
                    next_State = STATE_START;

                else if (sig_Rinse_Completed == 1) 
                    next_State = STATE_SPIN;
                    
                else if (sig_Motor_Failure == 1) 
                    next_State = STATE_FAULT;
            
                else 
                    next_State = STATE_RINSE;
            end
            STATE_SPIN: begin
                if (sig_Cancel == 1)
                    next_State = STATE_START;

                else if (sig_Spin_Completed == 1) 
                    next_State = STATE_START;
                    
                else if (sig_Motor_Failure == 1 | sig_Out_Of_Balance == 1) 
                    next_State = STATE_FAULT;
                
                else 
                    next_State = STATE_SPIN;
            end
            STATE_FAULT:
                next_State = STATE_READY;
            
            default: 
                next_State = STATE_START;
        endcase
    end
    else if (input2) begin
        case (state)
            STATE_START: begin
                if (sig_Coin == 1)
                    next_State = STATE_READY;

                else 
                    next_State = STATE_START;
            end
            STATE_READY: begin
                if (sig_Lid_Closed == 1)
                    next_State = STATE_FILL_WATER;

                else if (sig_Cancel == 1)
                    next_State = STATE_START;
            end
            STATE_FILL_WATER: begin
                if (sig_Cancel == 1)
                    next_State = STATE_START;

                else if (sig_Full == 1)
                    next_State = STATE_HEAT_WATER;
                
                else if (sig_Time_Out == 1)
                    next_State = STATE_FAULT;
                
                else 
                    next_State = STATE_FILL_WATER;
            end
            STATE_HEAT_WATER: begin
                if (sig_Cancel == 1)
                    next_State = STATE_START;

                else if (sig_Temperature == 1) 
                    next_State = STATE_WASH;
                    
                else if (sig_Time_Out == 1) 
                    next_State = STATE_FAULT;
                
                else 
                    next_State = STATE_HEAT_WATER;
            end
            STATE_WASH: begin
                if (sig_Cancel == 1)
                    next_State = STATE_START;

                else if (sig_Wash_Completed == 1) 
                    next_State = STATE_RINSE;
                    
                else if (sig_Out_Of_Balance == 1)
                    next_State = STATE_FAULT;
        
                else 
                    next_State = STATE_WASH;
            end
            STATE_RINSE: begin
                if (sig_Cancel == 1)
                    next_State = STATE_START;

                else if (sig_Rinse_Completed == 1) 
                    next_State = STATE_START;
                    
                else if (sig_Motor_Failure == 1) 
                    next_State = STATE_FAULT;
            
                else 
                    next_State = STATE_RINSE;
            end
            STATE_FAULT:
                next_State = STATE_READY;
            
            default: 
                next_State = STATE_START;
        endcase
    end
    else if (input3) begin
        case (state)
            STATE_START: begin
                if (sig_Coin == 1)
                    next_State = STATE_READY;

                else 
                    next_State = STATE_START;
            end
            STATE_READY: begin
                if (sig_Lid_Closed == 1)
                    next_State = STATE_RINSE;

                else if (sig_Cancel == 1)
                    next_State = STATE_START;
            end
            STATE_RINSE: begin
                if (sig_Cancel == 1)
                    next_State = STATE_START;

                else if (sig_Rinse_Completed == 1) 
                    next_State = STATE_SPIN;
                    
                else if (sig_Motor_Failure == 1) 
                    next_State = STATE_FAULT;
            
                else 
                    next_State = STATE_RINSE;
            end
            STATE_SPIN: begin
                if (sig_Cancel == 1)
                    next_State = STATE_START;

                else if (sig_Spin_Completed == 1) 
                    next_State = STATE_START;
                    
                else if (sig_Motor_Failure == 1 | sig_Out_Of_Balance == 1) 
                    next_State = STATE_FAULT;
                
                else 
                    next_State = STATE_SPIN;
            end
            STATE_FAULT:
                next_State = STATE_READY;
            
            default: 
                next_State = STATE_START;
        endcase
        
    end
    else if (input4) begin
        case (state)
            STATE_START: begin
                if (sig_Coin == 1)
                    next_State = STATE_READY;

                else 
                    next_State = STATE_START;
            end
            STATE_READY: begin
                if (sig_Lid_Closed == 1)
                    next_State = STATE_FILL_WATER;

                else if (sig_Cancel == 1)
                    next_State = STATE_START;
            end
            STATE_FILL_WATER: begin
                if (sig_Cancel == 1)
                    next_State = STATE_START;

                else if (sig_Full == 1)
                    next_State = STATE_WASH;
                
                else if (sig_Time_Out == 1)
                    next_State = STATE_FAULT;
                
                else 
                    next_State = STATE_FILL_WATER;
            end
            STATE_WASH: begin
                if (sig_Cancel == 1)
                    next_State = STATE_START;

                else if (sig_Wash_Completed == 1) 
                    next_State = STATE_RINSE;
                    
                else if (sig_Out_Of_Balance == 1)
                    next_State = STATE_FAULT;
        
                else 
                    next_State = STATE_WASH;
            end
            STATE_RINSE: begin
                if (sig_Cancel == 1)
                    next_State = STATE_START;

                else if (sig_Rinse_Completed == 1) 
                    next_State = STATE_SPIN;
                    
                else if (sig_Motor_Failure == 1) 
                    next_State = STATE_FAULT;
            
                else 
                    next_State = STATE_RINSE;
            end
            STATE_SPIN: begin
                if (sig_Cancel == 1)
                    next_State = STATE_START;

                else if (sig_Spin_Completed == 1) 
                    next_State = STATE_START;
                    
                else if (sig_Motor_Failure == 1 | sig_Out_Of_Balance == 1) 
                    next_State = STATE_FAULT;
                
                else 
                    next_State = STATE_SPIN;
            end
            STATE_FAULT:
                next_State = STATE_READY;
            
            default: 
                next_State = STATE_START;
        endcase
    end
    else if (input5) begin
        case (state)
            STATE_START: begin
                if (sig_Coin == 1)
                    next_State = STATE_READY;

                else 
                    next_State = STATE_START;
            end
            STATE_READY: begin
                if (sig_Lid_Closed == 1)
                    next_State = STATE_FILL_WATER;

                else if (sig_Cancel == 1)
                    next_State = STATE_START;
            end
            STATE_FILL_WATER: begin
                if (sig_Cancel == 1)
                    next_State = STATE_START;

                else if (sig_Full == 1)
                    next_State = STATE_WASH;
                
                else if (sig_Time_Out == 1)
                    next_State = STATE_FAULT;
                
                else 
                    next_State = STATE_FILL_WATER;
            end
            STATE_WASH: begin
                if (sig_Cancel == 1)
                    next_State = STATE_START;

                else if (sig_Wash_Completed == 1) 
                    next_State = STATE_RINSE;
                    
                else if (sig_Out_Of_Balance == 1)
                    next_State = STATE_FAULT;
        
                else 
                    next_State = STATE_WASH;
            end
            STATE_RINSE: begin
                if (sig_Cancel == 1)
                    next_State = STATE_START;

                else if (sig_Rinse_Completed == 1) 
                    next_State = STATE_START;
                    
                else if (sig_Motor_Failure == 1) 
                    next_State = STATE_FAULT;
            
                else 
                    next_State = STATE_RINSE;
            end
            STATE_FAULT:
                next_State = STATE_READY;
            
            default: 
                next_State = STATE_START;
        endcase
        

    end

    else if (input6) begin
        case (state)
            STATE_START: begin
                if (sig_Coin == 1)
                    next_State = STATE_READY;

                else 
                    next_State = STATE_START;
            end
            STATE_READY: begin
                if (sig_Lid_Closed == 1)
                    next_State = STATE_SPIN;

                else if (sig_Cancel == 1)
                    next_State = STATE_START;
            end
            STATE_SPIN: begin
                if (sig_Cancel == 1)
                    next_State = STATE_START;

                else if (sig_Spin_Completed == 1) 
                    next_State = STATE_START;
                    
                else if (sig_Motor_Failure == 1 | sig_Out_Of_Balance == 1) 
                    next_State = STATE_FAULT;
                
                else 
                    next_State = STATE_SPIN;
            end
            STATE_FAULT:
                next_State = STATE_READY;
            
            default: 
                next_State = STATE_START;
        endcase
    end
    end

    assign start = (state == STATE_START) ? 1'b1 : 1'b0;
    assign ready = (state == STATE_READY) ? 1'b1 : 1'b0;
    assign fill_Water_Operation = (state == STATE_FILL_WATER)? 1'b1: 1'b0;
    assign heat_Water_Operation = (state == STATE_HEAT_WATER)? 1'b1: 1'b0;
    assign wash_Operation = (state == STATE_WASH)? 1'b1: 1'b0;
    assign rinse_Operation = (state == STATE_RINSE)? 1'b1: 1'b0;
    assign spin_Operation = (state ==STATE_SPIN)? 1'b1: 1'b0;
    assign fault = (state == STATE_FAULT)? 1'b1: 1'b0;
    assign coin_Return = (state == STATE_READY)? 1'b1: 1'b0;
    assign water_Intake = ((state == STATE_FILL_WATER) || (state == STATE_RINSE))? 1'b1: 1'b0;
    assign fault_Cleared = (state == STATE_FAULT)? 1'b1: 1'b0;

endmodule

designs_n_tb/9_washing_machine_controller/timer.v
// ref: https://github.com/yasnakateb/WMController
module Timer (
    clock,
    state,
    sig_Full,
    sig_Temperature,
    sig_Wash_Completed,
    sig_Rinse_Completed,
    sig_Spin_Completed,
    );
    
    input clock;

    input [2:0] state;
    
    output sig_Full;
    output sig_Temperature;
    output sig_Wash_Completed;
    output sig_Rinse_Completed;
    output sig_Spin_Completed;
    
    reg sig_Full;
    reg sig_Temperature;
    reg sig_Wash_Completed;
    reg sig_Rinse_Completed;
    reg sig_Spin_Completed;

    reg [1:0] fill_Water_Counter;
    reg [1:0] heat_Water_Counter;
    reg [2:0] wash_Counter;
    reg [1:0] rinse_Counter;
    reg [1:0] spin_Counter;

    parameter STATE_START = 3'd0;
    parameter STATE_READY = 3'd1;
    parameter STATE_FILL_WATER = 3'd2;
    parameter STATE_HEAT_WATER = 3'd3;
    parameter STATE_WASH = 3'd4;
    parameter STATE_RINSE = 3'd5;
    parameter STATE_SPIN = 3'd6;

    parameter FULL_WATER_TIME = 2'd2;
    parameter REQUIRED_TEMPERATURE_TIME = 2'd3;
    parameter WASH_TIME = 3'd5;
    parameter RINSE_TIME = 2'd3;
    parameter SPIN_TIME = 2'd3;


    always @ (posedge clock) begin 
        if (fill_Water_Counter == FULL_WATER_TIME)
            sig_Full = 1;

        if (heat_Water_Counter == REQUIRED_TEMPERATURE_TIME) 
            sig_Temperature = 1;
        
        if (wash_Counter == WASH_TIME)
            sig_Wash_Completed = 1;
        if (rinse_Counter == RINSE_TIME)
            sig_Rinse_Completed = 1;
        if (spin_Counter == SPIN_TIME)
            sig_Spin_Completed = 1; 
        if (state == STATE_START || state == STATE_READY) begin
            fill_Water_Counter = 0;
            heat_Water_Counter = 0;
            wash_Counter = 0;
            rinse_Counter = 0;
            spin_Counter = 0;
            sig_Full = 0;
            sig_Temperature = 0;
            sig_Wash_Completed = 0;
            sig_Rinse_Completed = 0;
            sig_Spin_Completed = 0; 
        end 

        case (state)
            STATE_FILL_WATER: 
                fill_Water_Counter = fill_Water_Counter + 1'd1;
                
            STATE_HEAT_WATER: 
                heat_Water_Counter = heat_Water_Counter + 1'd1;
                
            STATE_WASH: 
                wash_Counter = wash_Counter + 1'd1;
                
            STATE_RINSE: 
                rinse_Counter = rinse_Counter + 1'd1;
                
            STATE_SPIN: 
                spin_Counter = spin_Counter + 1'd1;
                
        endcase
    end                    

endmodule

designs_n_tb/9_washing_machine_controller/Microcontroller.v
`include "controller.v"
`include "timer.v"
// ref: https://github.com/yasnakateb/WMController
module Microcontroller(
    clock,
    input1,
    input2,
    input3,
    input4,
    input5,
    input6,
    sig_Lid_Closed,
    sig_Coin,
    sig_Cancel,
    sig_Time_Out,
    sig_Out_Of_Balance,
    sig_Motor_Failure,
    state
    );

    input clock;

    input sig_Lid_Closed;
    input sig_Coin;

    input sig_Cancel;
    input sig_Time_Out;
    input sig_Out_Of_Balance;
    input sig_Motor_Failure;

    input input1;
    input input2;
    input input3;
    input input4;
    input input5;
    input input6;

    output [2:0] state;
 
    
    wire start;
    wire ready;
    wire fill_Water_Operation;
    wire heat_Water_Operation;
    wire wash_Operation;
    wire rinse_Operation;
    wire spin_Operation;
    wire fault;
    wire coin_Return;
    wire water_Intake;
    wire fault_Cleared;

    wire sig_Full;
    wire sig_Temperature;
    wire sig_Wash_Completed;
    wire sig_Rinse_Completed;
    wire sig_Spin_Completed;
 

Timer timer (
    .clock(clock),
    .state(state),

    .sig_Full(sig_Full),
    .sig_Temperature(sig_Temperature),
    .sig_Wash_Completed(sig_Wash_Completed),
    .sig_Rinse_Completed(sig_Rinse_Completed),
    .sig_Spin_Completed(sig_Spin_Completed)
    ); 


Controller controller(
    .clock(clock),
    .input1(input1),
    .input2(input2),
    .input3(input3),
    .input4(input4),
    .input5(input5),
    .input6(input6),
    .sig_Lid_Closed(sig_Lid_Closed),
    .sig_Coin(sig_Coin),

    .sig_Cancel(sig_Cancel),
    .sig_Time_Out(sig_Time_Out),
    .sig_Out_Of_Balance(sig_Out_Of_Balance),
    .sig_Motor_Failure(sig_Motor_Failure),

    .sig_Full(sig_Full),
    .sig_Temperature(sig_Temperature),
    .sig_Wash_Completed(sig_Wash_Completed),
    .sig_Rinse_Completed(sig_Rinse_Completed),
    .sig_Spin_Completed(sig_Spin_Completed),

    .start(start),
    .ready(ready),
    .fill_Water_Operation(fill_Water_Operation),
    .heat_Water_Operation(heat_Water_Operation),
    .wash_Operation(wash_Operation),
    .rinse_Operation(rinse_Operation),
    .spin_Operation(spin_Operation),
    .fault(fault),
    .coin_Return(coin_Return),
    .water_Intake(water_Intake),
    .fault_Cleared(fault_Cleared),
    .state(state)
    );       

endmodule

designs_n_tb/9_washing_machine_controller/Washing_machine_tb.v
// ref: https://github.com/yasnakateb/WMController
`include "Microcontroller.v"
module Microcontroller_tb();
    reg clock;
    reg input1;
    reg input2;
    reg input3;
    reg input4;
    reg input5;
    reg input6;
    reg sig_Lid_Closed;
    reg sig_Coin;
    reg sig_Cancel;
    reg sig_Time_Out;
    reg sig_Out_Of_Balance;
    reg sig_Motor_Failure;
    wire [2:0] state;

Microcontroller uut(
    .clock(clock),
    .input1(input1),
    .input2(input2),
    .input3(input3),
    .input4(input4),
    .input5(input5),
    .input6(input6),
    .sig_Lid_Closed(sig_Lid_Closed),
    .sig_Coin(sig_Coin),
    .sig_Cancel(sig_Cancel),
    .sig_Time_Out(sig_Time_Out),
    .sig_Out_Of_Balance(sig_Out_Of_Balance),
    .sig_Motor_Failure(sig_Motor_Failure),
    .state(state)
    );

    always #1 clock = ~ clock;

    initial begin 
    $dumpfile("Microcontroller_tb.vcd");
    $dumpvars(0,Microcontroller_tb);

        clock = 0;
        sig_Coin = 1;
        sig_Lid_Closed = 1;
        input1 = 0;
        input2 = 1;
        input3 = 0;
        input4 = 0;
        input5 = 0;
        input6 = 0;

        #100
        input2 = 0;
        input6 = 1;
    end

    initial #1000 $finish;

endmodule

designs_n_tb/9_washing_machine_controller/Microcontroller_tb.vcd
$date
	Tue Jul 18 15:25:14 2023
$end
$version
	Icarus Verilog
$end
$timescale
	1s
$end
$scope module Microcontroller_tb $end
$var wire 3 ! state [2:0] $end
$var reg 1 " clock $end
$var reg 1 # input1 $end
$var reg 1 $ input2 $end
$var reg 1 % input3 $end
$var reg 1 & input4 $end
$var reg 1 ' input5 $end
$var reg 1 ( input6 $end
$var reg 1 ) sig_Cancel $end
$var reg 1 * sig_Coin $end
$var reg 1 + sig_Lid_Closed $end
$var reg 1 , sig_Motor_Failure $end
$var reg 1 - sig_Out_Of_Balance $end
$var reg 1 . sig_Time_Out $end
$scope module uut $end
$var wire 1 " clock $end
$var wire 1 # input1 $end
$var wire 1 $ input2 $end
$var wire 1 % input3 $end
$var wire 1 & input4 $end
$var wire 1 ' input5 $end
$var wire 1 ( input6 $end
$var wire 1 ) sig_Cancel $end
$var wire 1 * sig_Coin $end
$var wire 1 + sig_Lid_Closed $end
$var wire 1 , sig_Motor_Failure $end
$var wire 1 - sig_Out_Of_Balance $end
$var wire 1 . sig_Time_Out $end
$var wire 1 / water_Intake $end
$var wire 1 0 wash_Operation $end
$var wire 3 1 state [2:0] $end
$var wire 1 2 start $end
$var wire 1 3 spin_Operation $end
$var wire 1 4 sig_Wash_Completed $end
$var wire 1 5 sig_Temperature $end
$var wire 1 6 sig_Spin_Completed $end
$var wire 1 7 sig_Rinse_Completed $end
$var wire 1 8 sig_Full $end
$var wire 1 9 rinse_Operation $end
$var wire 1 : ready $end
$var wire 1 ; heat_Water_Operation $end
$var wire 1 < fill_Water_Operation $end
$var wire 1 = fault_Cleared $end
$var wire 1 > fault $end
$var wire 1 ? coin_Return $end
$scope module controller $end
$var wire 1 " clock $end
$var wire 1 # input1 $end
$var wire 1 $ input2 $end
$var wire 1 % input3 $end
$var wire 1 & input4 $end
$var wire 1 ' input5 $end
$var wire 1 ( input6 $end
$var wire 1 ) sig_Cancel $end
$var wire 1 * sig_Coin $end
$var wire 1 + sig_Lid_Closed $end
$var wire 1 , sig_Motor_Failure $end
$var wire 1 - sig_Out_Of_Balance $end
$var wire 1 . sig_Time_Out $end
$var wire 1 / water_Intake $end
$var wire 1 0 wash_Operation $end
$var wire 1 2 start $end
$var wire 1 3 spin_Operation $end
$var wire 1 4 sig_Wash_Completed $end
$var wire 1 5 sig_Temperature $end
$var wire 1 6 sig_Spin_Completed $end
$var wire 1 7 sig_Rinse_Completed $end
$var wire 1 8 sig_Full $end
$var wire 1 9 rinse_Operation $end
$var wire 1 : ready $end
$var wire 1 ; heat_Water_Operation $end
$var wire 1 < fill_Water_Operation $end
$var wire 1 = fault_Cleared $end
$var wire 1 > fault $end
$var wire 1 ? coin_Return $end
$var reg 3 @ next_State [2:0] $end
$var reg 3 A state [2:0] $end
$upscope $end
$scope module timer $end
$var wire 1 " clock $end
$var wire 3 B state [2:0] $end
$var reg 2 C fill_Water_Counter [1:0] $end
$var reg 2 D heat_Water_Counter [1:0] $end
$var reg 2 E rinse_Counter [1:0] $end
$var reg 1 8 sig_Full $end
$var reg 1 7 sig_Rinse_Completed $end
$var reg 1 6 sig_Spin_Completed $end
$var reg 1 5 sig_Temperature $end
$var reg 1 4 sig_Wash_Completed $end
$var reg 2 F spin_Counter [1:0] $end
$var reg 3 G wash_Counter [2:0] $end
$upscope $end
$upscope $end
$upscope $end
$enddefinitions $end
#0
$dumpvars
bx G
bx F
bx E
bx D
bx C
b0 B
b0 A
bx @
0?
0>
0=
0<
0;
0:
09
x8
x7
x6
x5
x4
03
12
b0 1
00
0/
x.
x-
x,
1+
1*
x)
0(
0'
0&
0%
1$
0#
0"
b0 !
$end
#1
02
1:
1?
06
07
04
05
08
b0 F
b0 E
b0 G
b0 D
b0 C
b1 !
b1 1
b1 A
b1 B
b1 @
1"
#2
0"
#3
b10 @
1"
#4
0"
#5
1/
0:
1<
0?
b1 C
b10 !
b10 1
b10 A
b10 B
1"
#6
0"
#7
b10 C
1"
#8
0"
#9
b11 C
18
1"
#10
0"
#11
b11 @
b0 C
1"
#12
0"
#13
0/
0<
1;
b1 D
b11 !
b11 1
b11 A
b11 B
1"
#14
0"
#15
b10 D
1"
#16
0"
#17
b11 D
1"
#18
0"
#19
b100 @
b0 D
15
1"
#20
0"
#21
0;
10
b1 G
b100 !
b100 1
b100 A
b100 B
1"
#22
0"
#23
b10 G
1"
#24
0"
#25
b11 G
1"
#26
0"
#27
b100 G
1"
#28
0"
#29
b101 G
1"
#30
0"
#31
b101 @
b110 G
14
1"
#32
0"
#33
1/
00
19
b1 E
b101 !
b101 1
b101 A
b101 B
1"
#34
0"
#35
b10 E
1"
#36
0"
#37
b11 E
1"
#38
0"
#39
b0 @
b0 E
17
1"
#40
0"
#41
0/
12
09
07
04
05
08
b0 G
b0 !
b0 1
b0 A
b0 B
1"
#42
0"
#43
b1 @
1"
#44
0"
#45
02
1:
1?
b1 !
b1 1
b1 A
b1 B
1"
#46
0"
#47
b10 @
1"
#48
0"
#49
1/
0:
1<
0?
b1 C
b10 !
b10 1
b10 A
b10 B
1"
#50
0"
#51
b10 C
1"
#52
0"
#53
b11 C
18
1"
#54
0"
#55
b11 @
b0 C
1"
#56
0"
#57
0/
0<
1;
b1 D
b11 !
b11 1
b11 A
b11 B
1"
#58
0"
#59
b10 D
1"
#60
0"
#61
b11 D
1"
#62
0"
#63
b100 @
b0 D
15
1"
#64
0"
#65
0;
10
b1 G
b100 !
b100 1
b100 A
b100 B
1"
#66
0"
#67
b10 G
1"
#68
0"
#69
b11 G
1"
#70
0"
#71
b100 G
1"
#72
0"
#73
b101 G
1"
#74
0"
#75
b101 @
b110 G
14
1"
#76
0"
#77
1/
00
19
b1 E
b101 !
b101 1
b101 A
b101 B
1"
#78
0"
#79
b10 E
1"
#80
0"
#81
b11 E
1"
#82
0"
#83
b0 @
b0 E
17
1"
#84
0"
#85
0/
12
09
07
04
05
08
b0 G
b0 !
b0 1
b0 A
b0 B
1"
#86
0"
#87
b1 @
1"
#88
0"
#89
02
1:
1?
b1 !
b1 1
b1 A
b1 B
1"
#90
0"
#91
b10 @
1"
#92
0"
#93
1/
0:
1<
0?
b1 C
b10 !
b10 1
b10 A
b10 B
1"
#94
0"
#95
b10 C
1"
#96
0"
#97
b11 C
18
1"
#98
0"
#99
b11 @
b0 C
1"
#100
0"
1(
0$
#101
0/
12
0<
08
b0 !
b0 1
b0 A
b0 B
b0 @
1"
#102
0"
#103
b1 @
1"
#104
0"
#105
02
1:
1?
b1 !
b1 1
b1 A
b1 B
1"
#106
0"
#107
b110 @
1"
#108
0"
#109
0:
13
0?
b1 F
b110 !
b110 1
b110 A
b110 B
1"
#110
0"
#111
b10 F
1"
#112
0"
#113
b11 F
1"
#114
0"
#115
b0 @
b0 F
16
1"
#116
0"
#117
12
03
06
b0 !
b0 1
b0 A
b0 B
1"
#118
0"
#119
b1 @
1"
#120
0"
#121
02
1:
1?
b1 !
b1 1
b1 A
b1 B
1"
#122
0"
#123
b110 @
1"
#124
0"
#125
0:
13
0?
b1 F
b110 !
b110 1
b110 A
b110 B
1"
#126
0"
#127
b10 F
1"
#128
0"
#129
b11 F
1"
#130
0"
#131
b0 @
b0 F
16
1"
#132
0"
#133
12
03
06
b0 !
b0 1
b0 A
b0 B
1"
#134
0"
#135
b1 @
1"
#136
0"
#137
02
1:
1?
b1 !
b1 1
b1 A
b1 B
1"
#138
0"
#139
b110 @
1"
#140
0"
#141
0:
13
0?
b1 F
b110 !
b110 1
b110 A
b110 B
1"
#142
0"
#143
b10 F
1"
#144
0"
#145
b11 F
1"
#146
0"
#147
b0 @
b0 F
16
1"
#148
0"
#149
12
03
06
b0 !
b0 1
b0 A
b0 B
1"
#150
0"
#151
b1 @
1"
#152
0"
#153
02
1:
1?
b1 !
b1 1
b1 A
b1 B
1"
#154
0"
#155
b110 @
1"
#156
0"
#157
0:
13
0?
b1 F
b110 !
b110 1
b110 A
b110 B
1"
#158
0"
#159
b10 F
1"
#160
0"
#161
b11 F
1"
#162
0"
#163
b0 @
b0 F
16
1"
#164
0"
#165
12
03
06
b0 !
b0 1
b0 A
b0 B
1"
#166
0"
#167
b1 @
1"
#168
0"
#169
02
1:
1?
b1 !
b1 1
b1 A
b1 B
1"
#170
0"
#171
b110 @
1"
#172
0"
#173
0:
13
0?
b1 F
b110 !
b110 1
b110 A
b110 B
1"
#174
0"
#175
b10 F
1"
#176
0"
#177
b11 F
1"
#178
0"
#179
b0 @
b0 F
16
1"
#180
0"
#181
12
03
06
b0 !
b0 1
b0 A
b0 B
1"
#182
0"
#183
b1 @
1"
#184
0"
#185
02
1:
1?
b1 !
b1 1
b1 A
b1 B
1"
#186
0"
#187
b110 @
1"
#188
0"
#189
0:
13
0?
b1 F
b110 !
b110 1
b110 A
b110 B
1"
#190
0"
#191
b10 F
1"
#192
0"
#193
b11 F
1"
#194
0"
#195
b0 @
b0 F
16
1"
#196
0"
#197
12
03
06
b0 !
b0 1
b0 A
b0 B
1"
#198
0"
#199
b1 @
1"
#200
0"
#201
02
1:
1?
b1 !
b1 1
b1 A
b1 B
1"
#202
0"
#203
b110 @
1"
#204
0"
#205
0:
13
0?
b1 F
b110 !
b110 1
b110 A
b110 B
1"
#206
0"
#207
b10 F
1"
#208
0"
#209
b11 F
1"
#210
0"
#211
b0 @
b0 F
16
1"
#212
0"
#213
12
03
06
b0 !
b0 1
b0 A
b0 B
1"
#214
0"
#215
b1 @
1"
#216
0"
#217
02
1:
1?
b1 !
b1 1
b1 A
b1 B
1"
#218
0"
#219
b110 @
1"
#220
0"
#221
0:
13
0?
b1 F
b110 !
b110 1
b110 A
b110 B
1"
#222
0"
#223
b10 F
1"
#224
0"
#225
b11 F
1"
#226
0"
#227
b0 @
b0 F
16
1"
#228
0"
#229
12
03
06
b0 !
b0 1
b0 A
b0 B
1"
#230
0"
#231
b1 @
1"
#232
0"
#233
02
1:
1?
b1 !
b1 1
b1 A
b1 B
1"
#234
0"
#235
b110 @
1"
#236
0"
#237
0:
13
0?
b1 F
b110 !
b110 1
b110 A
b110 B
1"
#238
0"
#239
b10 F
1"
#240
0"
#241
b11 F
1"
#242
0"
#243
b0 @
b0 F
16
1"
#244
0"
#245
12
03
06
b0 !
b0 1
b0 A
b0 B
1"
#246
0"
#247
b1 @
1"
#248
0"
#249
02
1:
1?
b1 !
b1 1
b1 A
b1 B
1"
#250
0"
#251
b110 @
1"
#252
0"
#253
0:
13
0?
b1 F
b110 !
b110 1
b110 A
b110 B
1"
#254
0"
#255
b10 F
1"
#256
0"
#257
b11 F
1"
#258
0"
#259
b0 @
b0 F
16
1"
#260
0"
#261
12
03
06
b0 !
b0 1
b0 A
b0 B
1"
#262
0"
#263
b1 @
1"
#264
0"
#265
02
1:
1?
b1 !
b1 1
b1 A
b1 B
1"
#266
0"
#267
b110 @
1"
#268
0"
#269
0:
13
0?
b1 F
b110 !
b110 1
b110 A
b110 B
1"
#270
0"
#271
b10 F
1"
#272
0"
#273
b11 F
1"
#274
0"
#275
b0 @
b0 F
16
1"
#276
0"
#277
12
03
06
b0 !
b0 1
b0 A
b0 B
1"
#278
0"
#279
b1 @
1"
#280
0"
#281
02
1:
1?
b1 !
b1 1
b1 A
b1 B
1"
#282
0"
#283
b110 @
1"
#284
0"
#285
0:
13
0?
b1 F
b110 !
b110 1
b110 A
b110 B
1"
#286
0"
#287
b10 F
1"
#288
0"
#289
b11 F
1"
#290
0"
#291
b0 @
b0 F
16
1"
#292
0"
#293
12
03
06
b0 !
b0 1
b0 A
b0 B
1"
#294
0"
#295
b1 @
1"
#296
0"
#297
02
1:
1?
b1 !
b1 1
b1 A
b1 B
1"
#298
0"
#299
b110 @
1"
#300
0"
#301
0:
13
0?
b1 F
b110 !
b110 1
b110 A
b110 B
1"
#302
0"
#303
b10 F
1"
#304
0"
#305
b11 F
1"
#306
0"
#307
b0 @
b0 F
16
1"
#308
0"
#309
12
03
06
b0 !
b0 1
b0 A
b0 B
1"
#310
0"
#311
b1 @
1"
#312
0"
#313
02
1:
1?
b1 !
b1 1
b1 A
b1 B
1"
#314
0"
#315
b110 @
1"
#316
0"
#317
0:
13
0?
b1 F
b110 !
b110 1
b110 A
b110 B
1"
#318
0"
#319
b10 F
1"
#320
0"
#321
b11 F
1"
#322
0"
#323
b0 @
b0 F
16
1"
#324
0"
#325
12
03
06
b0 !
b0 1
b0 A
b0 B
1"
#326
0"
#327
b1 @
1"
#328
0"
#329
02
1:
1?
b1 !
b1 1
b1 A
b1 B
1"
#330
0"
#331
b110 @
1"
#332
0"
#333
0:
13
0?
b1 F
b110 !
b110 1
b110 A
b110 B
1"
#334
0"
#335
b10 F
1"
#336
0"
#337
b11 F
1"
#338
0"
#339
b0 @
b0 F
16
1"
#340
0"
#341
12
03
06
b0 !
b0 1
b0 A
b0 B
1"
#342
0"
#343
b1 @
1"
#344
0"
#345
02
1:
1?
b1 !
b1 1
b1 A
b1 B
1"
#346
0"
#347
b110 @
1"
#348
0"
#349
0:
13
0?
b1 F
b110 !
b110 1
b110 A
b110 B
1"
#350
0"
#351
b10 F
1"
#352
0"
#353
b11 F
1"
#354
0"
#355
b0 @
b0 F
16
1"
#356
0"
#357
12
03
06
b0 !
b0 1
b0 A
b0 B
1"
#358
0"
#359
b1 @
1"
#360
0"
#361
02
1:
1?
b1 !
b1 1
b1 A
b1 B
1"
#362
0"
#363
b110 @
1"
#364
0"
