designs_n_tb/5_Full_adder_/full_adder.v
module full_adder(input a, b, cin, output sum, cout);

//input a,b,cin;
//output sum, cout;

//reg cout1, cout2, cout3;
	//assign cout1 = a & b;
	//assign cout2 = a & cin;
	//assign cout3 = b & cin;
	assign cout = (a&b) | (a&cin) | (b&cin);

	assign sum = a ^ b ^ cin;

endmodule

designs_n_tb/5_Full_adder_/full_adder_tb.v
`include "full_adder.v"
module full_adder_tb; 

reg tba, tbb, tbcin;
wire tbsum, tbcout;
reg i;

full_adder DUT(.a(tba), .b(tbb), .cin(tbcin), .sum(tbsum), .cout(tbcout));


parameter timestamp = 80, timestamp1=timestamp/2,timestamp2=timestamp/4,timestamp3=timestamp/8;

initial 
#timestamp
$finish;

initial begin
	tba=1;
	#timestamp1;
	tba=0;
	end
initial begin
	tbb   = 0;
	forever 
	#timestamp2
	tbb   = ~tbb;
	end
initial begin
	tbcin = 0; 
	forever
	#timestamp3
	tbcin = ~tbcin;
	end
initial begin
	$dumpfile("full_adder.vcd");
	$dumpvars;
	end
endmodule

designs_n_tb/5_Full_adder_/full_adder.vcd
$date
	Mon Jul 10 16:51:51 2023
$end
$version
	Icarus Verilog
$end
$timescale
	1s
$end
$scope module full_adder_tb $end
$var wire 1 ! tbsum $end
$var wire 1 " tbcout $end
$var reg 1 # tba $end
$var reg 1 $ tbb $end
$var reg 1 % tbcin $end
$scope module DUT $end
$var wire 1 # a $end
$var wire 1 $ b $end
$var wire 1 % cin $end
$var wire 1 " cout $end
$var wire 1 ! sum $end
$upscope $end
$upscope $end
$enddefinitions $end
#0
$dumpvars
0%
0$
1#
0"
1!
$end
#10
1"
0!
1%
#20
0%
1$
#30
1!
1%
#40
0"
0!
0%
0$
0#
#50
1!
1%
#60
0%
1$
#70
1"
0!
1%
#80
0"
0%
0$
