designs_n_tb/7_JK_flipflop_/JK_flipflop.v
module JK_flipflop(input j,k,clk,output yout);

reg yout;

always @ (posedge clk)
case({j,k})
2'b00 : yout <= yout;
2'b01 : yout <= 0;
2'b10 : yout <= 1;
2'b11 : yout <= ~yout;
endcase

endmodule

designs_n_tb/7_JK_flipflop_/JK_flipflop_tb.v
`include "JK_flipflop.v"
module JK_flipflop_tb;

reg tbj, tbk, tbclk;

//wire tbyout;

always #11 tbclk = ~tbclk;

JK_flipflop DUT(.j(tbj), .k(tbk), .clk(tbclk), .yout(tbyout) );

initial
    #100
    $finish;
initial begin
    tbj = 0;
    tbclk = 0;
    forever 
        #20 
        tbj = ~tbj;
end
initial begin
    tbk = 0;
    forever
        #40 
        tbk = ~tbk;
end
initial begin
    $dumpfile("JK_flipflop.vcd");
    $dumpvars;
end
endmodule

designs_n_tb/7_JK_flipflop_/JK_flipflop.vcd
$date
	Mon Jul 10 17:52:17 2023
$end
$version
	Icarus Verilog
$end
$timescale
	1s
$end
$scope module JK_flipflop_tb $end
$var wire 1 ! tbyout $end
$var reg 1 " tbclk $end
$var reg 1 # tbj $end
$var reg 1 $ tbk $end
$scope module DUT $end
$var wire 1 " clk $end
$var wire 1 # j $end
$var wire 1 $ k $end
$var reg 1 ! yout $end
$upscope $end
$upscope $end
$enddefinitions $end
#0
$dumpvars
0$
0#
0"
x!
$end
#11
1"
#20
1#
#22
0"
#33
1!
1"
#40
0#
1$
#44
0"
#55
0!
1"
#60
1#
#66
0"
#77
1!
1"
#80
0#
0$
#88
0"
#99
1"
#100
1#
