designs_n_tb/8_Traffic_light_controller_/traffic_light_controller_non_uniform.v
module traffic_light_controller( input clk, mode, output reg [11:0] lightout);
// lightout has 12 bits output describing, north (MSB), east, south, west 
// each three bits in order, green, yellow, red, for north green signal: 4111 is output in octal
parameter   lightout_ng = 12'b100_001_001_001,// n green remaining red 4111 in octal
            lightout_ny = 12'b010_001_001_010,// n and w yellow: 2112
            lightout_wg = 12'b001_001_001_100,// w green       : 1114
            lightout_wy = 12'b001_010_001_010,// w and e yellow: 1212
            lightout_eg = 12'b001_100_001_001,// e green       : 1411
            lightout_ey = 12'b001_010_010_001,// e and s yellow: 1221
            lightout_sg = 12'b001_001_100_001,// s green       : 1121
            lightout_sy = 12'b010_001_010_001;// s and n yellow: 2121

reg real    timer1      = 50;// 50 seconds green light time //
reg real    timer2      = 30;// 30 seconds green light for minor traffic
reg real    timer4      = 120;// 120 seconds green light for major
reg real    timer30     = 10;// 10 seconds yellow light time
reg real    timer31     = 9;
reg real    start_timer, elapsed_time, timer, next_timer;// start the cycle from NORTH
reg integer flag, next_flag;// flag = 1 for green, flag = 2 for yellow,
reg [11:0] next_lightout;

initial begin
    timer        = timer4;
    next_timer   = timer31;
    lightout     = lightout_ng;
    next_lightout= lightout_ny;
    start_timer  = $time;
end

always @(posedge clk)
begin 
    elapsed_time = $time - start_timer;
    if (elapsed_time >= timer)
        begin
            lightout    = next_lightout;
            timer       = next_timer;
            start_timer = $time;
            
            case(mode)

            1:begin
            case (next_timer)
                timer1:  next_timer  = timer30;
                timer4:  next_timer  = timer31;
                timer31: next_timer  = timer1;
                timer30: next_timer  = timer4;
            endcase
            end
            0:begin
            case (next_timer)
                timer1: next_timer  = timer30;
                timer30: next_timer  = timer1;
            endcase
            end
            endcase


            case (next_lightout)
                lightout_ng: next_lightout = lightout_ny;
                lightout_ny: next_lightout = lightout_wg;
                lightout_wg: next_lightout = lightout_wy;
                lightout_wy: next_lightout = lightout_eg;
                lightout_eg: next_lightout = lightout_ey;
                lightout_ey: next_lightout = lightout_sg;
                lightout_sg: next_lightout = lightout_sy;
                lightout_sy: next_lightout = lightout_ng;
                default:     next_lightout = lightout_ng;
            endcase
        end
end
endmodule

designs_n_tb/8_Traffic_light_controller_/traffic_light_controller_tb.v
`include "traffic_light_controller_non_uniform.v"
module traffic_light_controller_tb;

reg tbclk, tbmode;

wire [11:0] tblightout;

always #10 tbclk = ~tbclk;

initial begin tbclk = 1'b0; tbmode = 1; end

traffic_light_controller DUT (.clk(tbclk),.mode(tbmode),.lightout(tblightout));

initial #500 $finish;

initial begin #150 tbmode = 0;#130 tbmode =1;end

initial begin
    $dumpfile("traffic.vcd");
    $dumpvars;
    end
endmodule

designs_n_tb/8_Traffic_light_controller_/traffic.vcd
$date
	Mon Jul 17 12:44:51 2023
$end
$version
	Icarus Verilog
$end
$timescale
	1s
$end
$scope module traffic_light_controller_tb $end
$var wire 12 ! tblightout [11:0] $end
$var reg 1 " tbclk $end
$var reg 1 # tbmode $end
$scope module DUT $end
$var wire 1 " clk $end
$var wire 1 # mode $end
$var reg 12 $ lightout [11:0] $end
$var reg 12 % next_lightout [11:0] $end
$var real 1 & elapsed_time $end
$var real 1 ' next_timer $end
$var real 1 ( start_timer $end
$var real 1 ) timer $end
$var real 1 * timer1 $end
$var real 1 + timer2 $end
$var real 1 , timer30 $end
$var real 1 - timer31 $end
$var real 1 . timer4 $end
$upscope $end
$upscope $end
$enddefinitions $end
#0
$dumpvars
r120 .
r9 -
r10 ,
r30 +
r50 *
r120 )
r0 (
r9 '
r0 &
b10001001010 %
b100001001001 $
1#
0"
b100001001001 !
$end
#10
r10 &
1"
#20
0"
#30
r30 &
1"
#40
0"
#50
r50 &
1"
#60
0"
#70
r70 &
1"
#80
0"
#90
r90 &
1"
#100
0"
#110
r110 &
1"
#120
0"
#130
b1001001100 %
r50 '
r130 (
r9 )
b10001001010 !
b10001001010 $
r130 &
1"
#140
0"
#150
b1010001010 %
r10 '
r150 (
r50 )
b1001001100 !
b1001001100 $
r20 &
1"
0#
#160
0"
#170
1"
#180
0"
#190
r40 &
1"
#200
0"
#210
b1100001001 %
r50 '
r210 (
r10 )
b1010001010 !
b1010001010 $
r60 &
1"
#220
0"
#230
b1010010001 %
r10 '
r230 (
r50 )
b1100001001 !
b1100001001 $
r20 &
1"
#240
0"
#250
1"
#260
0"
#270
r40 &
1"
#280
0"
1#
#290
b1001100001 %
r120 '
r290 (
r10 )
b1010010001 !
b1010010001 $
r60 &
1"
#300
0"
#310
b10001010001 %
r9 '
r310 (
r120 )
b1001100001 !
b1001100001 $
r20 &
1"
#320
0"
#330
1"
#340
0"
#350
r40 &
1"
#360
0"
#370
r60 &
1"
#380
0"
#390
r80 &
1"
#400
0"
#410
r100 &
1"
#420
0"
#430
b100001001001 %
r50 '
r430 (
r9 )
b10001010001 !
b10001010001 $
r120 &
1"
#440
0"
#450
b10001001010 %
r10 '
r450 (
r50 )
b100001001001 !
b100001001001 $
r20 &
1"
#460
0"
#470
1"
#480
0"
#490
r40 &
1"
