designs_n_tb/17_UART/source_files/baud_rate_generator.v
module baud_rate_gen (
  input clk,
  input start,
  input rx,
  input [31:0] divisor,
  input areset,
  output out
);
  reg [31:0] counter;
  reg temp_out;
  always @(posedge clk or posedge areset)
    begin
      if (areset)
        counter <= 32'd0;
      else if (start & ~(counter==divisor))
        counter <= counter + 32'd1;
      else if (~start)
        counter <= 32'd0;
      else if (counter==divisor)
        counter <= 32'd0;
      else
        counter <= counter;
    end
  assign out = (counter == divisor);
endmodule

designs_n_tb/17_UART/baud_tester.v
`include "baud_rate_generator.v"
module baud_tester();

reg tbclk, tbstart, tbrx;
reg [31:0] tbdivisor;

reg tbareset;
wire tbout;

initial #1000 $finish;

baud_rate_gen bd(
    tbclk, 
    tbstart,
    tbrx,
    tbdivisor,
    tbareset,
    tbout
);

initial tbclk =  1'b0;
always #1 tbclk = ~tbclk;

initial begin
    tbstart = 1;
    tbdivisor = 100;
    tbareset = 1;
    #10 tbareset = 0;
end

initial begin
    $dumpfile("dump.vcd");
    $dumpvars;
end
endmodule

designs_n_tb/17_UART/dump.vcd
$date
	Thu Aug 10 17:58:17 2023
$end
$version
	Icarus Verilog
$end
$timescale
	1s
$end
$scope module baud_tester $end
$var wire 1 ! tbout $end
$var reg 1 " tbareset $end
$var reg 1 # tbclk $end
$var reg 32 $ tbdivisor [31:0] $end
$var reg 1 % tbrx $end
$var reg 1 & tbstart $end
$scope module bd $end
$var wire 1 " areset $end
$var wire 1 # clk $end
$var wire 32 ' divisor [31:0] $end
$var wire 1 % rx $end
$var wire 1 & start $end
$var wire 1 ! out $end
$var reg 32 ( counter [31:0] $end
$upscope $end
$upscope $end
$enddefinitions $end
#0
$dumpvars
b0 (
b1100100 '
1&
x%
b1100100 $
0#
1"
0!
$end
#1
1#
#2
0#
#3
1#
#4
0#
#5
1#
#6
0#
#7
1#
#8
0#
#9
1#
#10
0#
0"
#11
b1 (
1#
#12
0#
#13
b10 (
1#
#14
0#
#15
b11 (
1#
#16
0#
#17
b100 (
1#
#18
0#
#19
b101 (
1#
#20
0#
#21
b110 (
1#
#22
0#
#23
b111 (
1#
#24
0#
#25
b1000 (
1#
#26
0#
#27
b1001 (
1#
#28
0#
#29
b1010 (
1#
#30
0#
#31
b1011 (
1#
#32
0#
#33
b1100 (
1#
#34
0#
#35
b1101 (
1#
#36
0#
#37
b1110 (
1#
#38
0#
#39
b1111 (
1#
#40
0#
#41
b10000 (
1#
#42
0#
#43
b10001 (
1#
#44
0#
#45
b10010 (
1#
#46
0#
#47
b10011 (
1#
#48
0#
#49
b10100 (
1#
#50
0#
#51
b10101 (
1#
#52
0#
#53
b10110 (
1#
#54
0#
#55
b10111 (
1#
#56
0#
#57
b11000 (
1#
#58
0#
#59
b11001 (
1#
#60
0#
#61
b11010 (
1#
#62
0#
#63
b11011 (
1#
#64
0#
#65
b11100 (
1#
#66
0#
#67
b11101 (
1#
#68
0#
#69
b11110 (
1#
#70
0#
#71
b11111 (
1#
#72
0#
#73
b100000 (
1#
#74
0#
#75
b100001 (
1#
#76
0#
#77
b100010 (
1#
#78
0#
#79
b100011 (
1#
#80
0#
#81
b100100 (
1#
#82
0#
#83
b100101 (
1#
#84
0#
#85
b100110 (
1#
#86
0#
#87
b100111 (
1#
#88
0#
#89
b101000 (
1#
#90
0#
#91
b101001 (
1#
#92
0#
#93
b101010 (
1#
#94
0#
#95
b101011 (
1#
#96
0#
#97
b101100 (
1#
#98
0#
#99
b101101 (
1#
#100
0#
#101
b101110 (
1#
#102
0#
#103
b101111 (
1#
#104
0#
#105
b110000 (
1#
#106
0#
#107
b110001 (
1#
#108
0#
#109
b110010 (
1#
#110
0#
#111
b110011 (
1#
#112
0#
#113
b110100 (
1#
#114
0#
#115
b110101 (
1#
#116
0#
#117
b110110 (
1#
#118
0#
#119
b110111 (
1#
#120
0#
#121
b111000 (
1#
#122
0#
#123
b111001 (
1#
#124
0#
#125
b111010 (
1#
#126
0#
#127
b111011 (
1#
#128
0#
#129
b111100 (
1#
#130
0#
#131
b111101 (
1#
#132
0#
#133
b111110 (
1#
#134
0#
#135
b111111 (
1#
#136
0#
#137
b1000000 (
1#
#138
0#
#139
b1000001 (
1#
#140
0#
#141
b1000010 (
1#
#142
0#
#143
b1000011 (
1#
#144
0#
#145
b1000100 (
1#
#146
0#
#147
b1000101 (
1#
#148
0#
#149
b1000110 (
1#
#150
0#
#151
b1000111 (
1#
#152
0#
#153
b1001000 (
1#
#154
0#
#155
b1001001 (
1#
#156
0#
#157
b1001010 (
1#
#158
0#
#159
b1001011 (
1#
#160
0#
#161
b1001100 (
1#
#162
0#
#163
b1001101 (
1#
#164
0#
#165
b1001110 (
1#
#166
0#
#167
b1001111 (
1#
#168
0#
#169
b1010000 (
1#
#170
0#
#171
b1010001 (
1#
#172
0#
#173
b1010010 (
1#
#174
0#
#175
b1010011 (
1#
#176
0#
#177
b1010100 (
1#
#178
0#
#179
b1010101 (
1#
#180
0#
#181
b1010110 (
1#
#182
0#
#183
b1010111 (
1#
#184
0#
#185
b1011000 (
1#
#186
0#
#187
b1011001 (
1#
#188
0#
#189
b1011010 (
1#
#190
0#
#191
b1011011 (
1#
#192
0#
#193
b1011100 (
1#
#194
0#
#195
b1011101 (
1#
#196
0#
#197
b1011110 (
1#
#198
0#
#199
b1011111 (
1#
#200
0#
#201
b1100000 (
1#
#202
0#
#203
b1100001 (
1#
#204
0#
#205
b1100010 (
1#
#206
0#
#207
b1100011 (
1#
#208
0#
#209
1!
b1100100 (
1#
#210
0#
#211
0!
b0 (
1#
#212
0#
#213
b1 (
1#
#214
0#
#215
b10 (
1#
#216
0#
#217
b11 (
1#
#218
0#
#219
b100 (
1#
#220
0#
#221
b101 (
1#
#222
0#
#223
b110 (
1#
#224
0#
#225
b111 (
1#
#226
0#
#227
b1000 (
1#
#228
0#
#229
b1001 (
1#
#230
0#
#231
b1010 (
1#
#232
0#
#233
b1011 (
1#
#234
0#
#235
b1100 (
1#
#236
0#
#237
b1101 (
1#
#238
0#
#239
b1110 (
1#
#240
0#
#241
b1111 (
1#
#242
0#
#243
b10000 (
1#
#244
0#
#245
b10001 (
1#
#246
0#
#247
b10010 (
1#
#248
0#
#249
b10011 (
1#
#250
0#
#251
b10100 (
1#
#252
0#
#253
b10101 (
1#
#254
0#
#255
b10110 (
1#
#256
0#
#257
b10111 (
1#
#258
0#
#259
b11000 (
1#
#260
0#
#261
b11001 (
1#
#262
0#
#263
b11010 (
1#
#264
0#
#265
b11011 (
1#
#266
0#
#267
b11100 (
1#
#268
0#
#269
b11101 (
1#
#270
0#
#271
b11110 (
1#
#272
0#
#273
b11111 (
1#
#274
0#
#275
b100000 (
1#
#276
0#
#277
b100001 (
1#
#278
0#
#279
b100010 (
1#
#280
0#
#281
b100011 (
1#
#282
0#
#283
b100100 (
1#
#284
0#
#285
b100101 (
1#
#286
0#
#287
b100110 (
1#
#288
0#
#289
b100111 (
1#
#290
0#
#291
b101000 (
1#
#292
0#
#293
b101001 (
1#
#294
0#
#295
b101010 (
1#
#296
0#
#297
b101011 (
1#
#298
0#
#299
b101100 (
1#
#300
0#
#301
b101101 (
1#
#302
0#
#303
b101110 (
1#
#304
0#
#305
b101111 (
1#
#306
0#
#307
b110000 (
1#
#308
0#
#309
b110001 (
1#
#310
0#
#311
b110010 (
1#
#312
0#
#313
b110011 (
1#
#314
0#
#315
b110100 (
1#
#316
0#
#317
b110101 (
1#
#318
0#
#319
b110110 (
1#
#320
0#
#321
b110111 (
1#
#322
0#
#323
b111000 (
1#
#324
0#
#325
b111001 (
1#
#326
0#
#327
b111010 (
1#
#328
0#
#329
b111011 (
1#
#330
0#
#331
b111100 (
1#
#332
0#
#333
b111101 (
1#
#334
0#
#335
b111110 (
1#
#336
0#
#337
b111111 (
1#
#338
0#
#339
b1000000 (
1#
#340
0#
#341
b1000001 (
1#
#342
0#
#343
b1000010 (
1#
#344
0#
#345
b1000011 (
1#
#346
0#
#347
b1000100 (
1#
#348
0#
#349
b1000101 (
1#
#350
0#
#351
b1000110 (
1#
#352
0#
#353
b1000111 (
1#
#354
0#
#355
b1001000 (
1#
#356
0#
#357
b1001001 (
1#
#358
0#
#359
b1001010 (
1#
#360
0#
#361
b1001011 (
1#
#362
0#
#363
b1001100 (
1#
#364
0#
#365
b1001101 (
1#
#366
0#
#367
b1001110 (
1#
#368
0#
#369
b1001111 (
1#
#370
0#
#371
b1010000 (
1#
#372
0#
#373
b1010001 (
1#
#374
0#
#375
b1010010 (
1#
#376
0#
#377
b1010011 (
1#
#378
0#
#379
b1010100 (
1#
#380
0#
#381
b1010101 (
1#
#382
0#
#383
b1010110 (
1#
#384
0#
#385
b1010111 (
1#
#386
0#
#387
b1011000 (
1#
#388
0#
#389
b1011001 (
1#
#390
0#
#391
b1011010 (
1#
#392
0#
#393
b1011011 (
1#
#394
0#
#395
b1011100 (
1#
#396
0#
#397
b1011101 (
1#
#398
0#
#399
b1011110 (
1#
#400
0#
#401
b1011111 (
1#
#402
0#
#403
b1100000 (
1#
#404
0#
#405
b1100001 (
1#
#406
0#
#407
b1100010 (
1#
#408
0#
#409
b1100011 (
1#
#410
0#
#411
1!
b1100100 (
1#
#412
0#
#413
0!
b0 (
1#
#414
0#
#415
b1 (
1#
#416
0#
#417
b10 (
1#
#418
0#
#419
b11 (
1#
#420
0#
#421
b100 (
1#
#422
0#
#423
b101 (
1#
#424
0#
#425
b110 (
1#
#426
0#
#427
b111 (
1#
#428
0#
#429
b1000 (
1#
#430
0#
#431
b1001 (
1#
#432
0#
#433
b1010 (
1#
#434
0#
#435
b1011 (
1#
#436
0#
#437
b1100 (
1#
#438
0#
#439
b1101 (
1#
#440
0#
#441
b1110 (
1#
#442
0#
#443
b1111 (
1#
#444
0#
#445
b10000 (
1#
#446
0#
#447
b10001 (
1#
#448
0#
#449
b10010 (
1#
#450
0#
#451
b10011 (
1#
#452
0#
#453
b10100 (
1#
#454
0#
#455
b10101 (
1#
#456
0#
#457
b10110 (
1#
#458
0#
#459
b10111 (
1#
#460
0#
#461
b11000 (
1#
#462
0#
#463
b11001 (
1#
#464
0#
#465
b11010 (
1#
#466
0#
#467
b11011 (
1#
#468
0#
#469
b11100 (
1#
#470
0#
#471
b11101 (
1#
#472
0#
#473
b11110 (
1#
#474
0#
#475
b11111 (
1#
#476
0#
#477
b100000 (
1#
#478
0#
#479
b100001 (
1#
#480
0#
#481
b100010 (
1#
#482
0#
#483
b100011 (
1#
#484
0#
#485
b100100 (
1#
#486
0#
#487
b100101 (
1#
#488
0#
#489
b100110 (
1#
#490
0#
#491
b100111 (
1#
#492
0#
#493
b101000 (
1#
#494
0#
#495
b101001 (
1#
#496
0#
#497
b101010 (
1#
#498
0#
#499
b101011 (
1#
#500
0#
#501
b101100 (
1#
#502
0#
#503
b101101 (
1#
#504
0#
#505
b101110 (
1#
#506
0#
#507
b101111 (
1#
#508
0#
#509
b110000 (
1#
#510
0#
#511
b110001 (
1#
#512
0#
#513
b110010 (
1#
#514
0#
#515
b110011 (
1#
#516
0#
#517
b110100 (
1#
#518
0#
#519
b110101 (
1#
#520
0#
#521
b110110 (
1#
#522
0#
#523
b110111 (
1#
#524
0#
#525
b111000 (
1#
#526
0#
#527
b111001 (
1#
#528
0#
#529
b111010 (
1#
#530
0#
#531
b111011 (
1#
#532
0#
#533
b111100 (
1#
#534
0#
#535
b111101 (
1#
#536
0#
#537
b111110 (
1#
#538
0#
#539
b111111 (
1#
#540
0#
#541
b1000000 (
1#
#542
0#
#543
b1000001 (
1#
#544
0#
#545
b1000010 (
1#
#546
0#
#547
b1000011 (
1#
#548
0#
#549
b1000100 (
1#
#550
0#
#551
b1000101 (
1#
#552
0#
#553
b1000110 (
1#
#554
0#
#555
b1000111 (
1#
#556
0#
#557
b1001000 (
1#
#558
0#
#559
b1001001 (
1#
#560
0#
#561
b1001010 (
1#
#562
0#
#563
b1001011 (
1#
#564
0#
#565
b1001100 (
1#
#566
0#
#567
b1001101 (
1#
#568
0#
#569
b1001110 (
1#
#570
0#
#571
b1001111 (
1#
#572
0#
#573
b1010000 (
1#
#574
0#
#575
b1010001 (
1#
#576
0#
#577
b1010010 (
1#
#578
0#
#579
b1010011 (
1#
#580
0#
#581
b1010100 (
1#
#582
0#
#583
b1010101 (
1#
#584
0#
#585
b1010110 (
1#
#586
0#
#587
b1010111 (
1#
#588
0#
#589
b1011000 (
1#
#590
0#
#591
b1011001 (
1#
#592
0#
#593
b1011010 (
1#
#594
0#
#595
b1011011 (
1#
#596
0#
#597
b1011100 (
1#
#598
0#
#599
b1011101 (
1#
#600
0#
#601
b1011110 (
1#
#602
0#
#603
b1011111 (
1#
#604
0#
#605
b1100000 (
1#
#606
0#
#607
b1100001 (
1#
#608
0#
#609
b1100010 (
1#
#610
0#
#611
b1100011 (
1#
#612
0#
#613
1!
b1100100 (
1#
#614
0#
#615
0!
b0 (
1#
#616
0#
#617
b1 (
1#
#618
0#
#619
b10 (
1#
#620
0#
#621
b11 (
1#
#622
0#
#623
b100 (
1#
#624
0#
#625
b101 (
1#
#626
0#
#627
b110 (
1#
#628
0#
#629
b111 (
1#
#630
0#
#631
b1000 (
1#
#632
0#
#633
b1001 (
1#
#634
0#
#635
b1010 (
1#
#636
0#
#637
b1011 (
1#
#638
0#
#639
b1100 (
1#
#640
0#
#641
b1101 (
1#
#642
0#
#643
b1110 (
1#
#644
0#
#645
b1111 (
1#
#646
0#
#647
b10000 (
1#
#648
0#
#649
b10001 (
1#
#650
0#
#651
b10010 (
1#
#652
0#
#653
b10011 (
1#
#654
0#
#655
b10100 (
1#
#656
0#
#657
b10101 (
1#
#658
0#
#659
b10110 (
1#
#660
0#
#661
b10111 (
1#
#662
0#
#663
b11000 (
1#
#664
0#
#665
b11001 (
1#
#666
0#
#667
b11010 (
1#
#668
0#
#669
b11011 (
1#
#670
0#
#671
b11100 (
1#
#672
0#
#673
b11101 (
1#
#674
0#
#675
b11110 (
1#
#676
0#
#677
b11111 (
1#
#678
0#
#679
b100000 (
1#
#680
0#
#681
b100001 (
1#
#682
0#
#683
b100010 (
1#
#684
0#
#685
b100011 (
1#
#686
0#
#687
b100100 (
1#
#688
0#
#689
b100101 (
1#
#690
0#
#691
b100110 (
1#
#692
0#
#693
b100111 (
1#
#694
0#
#695
b101000 (
1#
#696
0#
#697
b101001 (
1#
#698
0#
#699
b101010 (
1#
#700
0#
#701
b101011 (
1#
#702
0#
#703
b101100 (
1#
#704
0#
#705
b101101 (
1#
#706
0#
#707
b101110 (
1#
#708
0#
#709
b101111 (
1#
#710
0#
#711
b110000 (
1#
#712
0#
#713
b110001 (
1#
#714
0#
#715
b110010 (
1#
#716
0#
#717
b110011 (
1#
#718
0#
#719
b110100 (
1#
#720
0#
#721
b110101 (
1#
#722
0#
#723
b110110 (
1#
#724
0#
#725
b110111 (
1#
#726
0#
#727
b111000 (
1#
#728
0#
#729
b111001 (
1#
#730
0#
#731
b111010 (
1#
#732
0#
#733
b111011 (
1#
#734
0#
#735
b111100 (
1#
#736
0#
#737
b111101 (
1#
#738
0#
#739
b111110 (
1#
#740
0#
#741
b111111 (
1#
#742
0#
#743
b1000000 (
1#
#744
0#
#745
b1000001 (
1#
#746
0#
#747
b1000010 (
1#
#748
0#
#749
b1000011 (
1#
#750
0#
#751
b1000100 (
1#
#752
0#
#753
b1000101 (
1#
#754
0#
#755
b1000110 (
1#
#756
0#
#757
b1000111 (
1#
#758
0#
#759
b1001000 (
1#
#760
0#
#761
b1001001 (
1#
#762
0#
#763
b1001010 (
1#
#764
0#
#765
b1001011 (
1#
#766
0#
#767
b1001100 (
1#
#768
0#
#769
b1001101 (
1#
#770
0#
#771
b1001110 (
1#
#772
0#
#773
b1001111 (
1#
#774
0#
#775
b1010000 (
1#
#776
0#
#777
b1010001 (
1#
#778
0#
#779
b1010010 (
1#
#780
0#
#781
b1010011 (
1#
#782
0#
#783
b1010100 (
1#
#784
0#
#785
b1010101 (
1#
#786
0#
#787
b1010110 (
1#
#788
0#
#789
b1010111 (
1#
#790
0#
#791
b1011000 (
1#
#792
0#
#793
b1011001 (
1#
#794
0#
#795
b1011010 (
1#
#796
0#
#797
b1011011 (
1#
#798
0#
#799
b1011100 (
1#
#800
0#
#801
b1011101 (
1#
#802
0#
#803
b1011110 (
1#
#804
0#
#805
b1011111 (
1#
#806
0#
#807
b1100000 (
1#
#808
0#
#809
b1100001 (
1#
#810
0#
#811
b1100010 (
1#
#812
0#
#813
b1100011 (
1#
#814
0#
#815
1!
b1100100 (
1#
#816
0#
#817
0!
b0 (
1#
#818
0#
#819
b1 (
1#
#820
0#
#821
b10 (
1#
#822
0#
#823
b11 (
1#
#824
0#
#825
b100 (
1#
#826
0#
#827
b101 (
1#
#828
0#
#829
b110 (
1#
#830
0#
#831
b111 (
1#
#832
0#
#833
b1000 (
1#
#834
0#
#835
b1001 (
1#
#836
0#
#837
b1010 (
1#
#838
0#
#839
b1011 (
1#
#840
0#
#841
b1100 (
1#
#842
0#
#843
b1101 (
1#
#844
0#
#845
b1110 (
1#
#846
0#
#847
b1111 (
1#
#848
0#
#849
b10000 (
1#
#850
0#
#851
b10001 (
1#
#852
0#
#853
b10010 (
1#
#854
0#
#855
b10011 (
1#
#856
0#
#857
b10100 (
1#
#858
0#
#859
b10101 (
1#
#860
0#
#861
b10110 (
1#
#862
0#
#863
b10111 (
1#
#864
0#
#865
b11000 (
1#
#866
0#
#867
b11001 (
1#
#868
0#
#869
b11010 (
1#
#870
0#
#871
b11011 (
1#
#872
0#
#873
b11100 (
1#
#874
0#
#875
b11101 (
1#
#876
0#
#877
b11110 (
1#
#878
0#
#879
b11111 (
1#
#880
0#
#881
b100000 (
1#
#882
0#
#883
b100001 (
1#
#884
0#
#885
b100010 (
1#
#886
0#
#887
b100011 (
1#
#888
0#
#889
b100100 (
1#
#890
0#
#891
b100101 (
1#
#892
0#
#893
b100110 (
1#
#894
0#
#895
b100111 (
1#
#896
0#
#897
b101000 (
1#
#898
0#
#899
b101001 (
1#
#900
0#
#901
b101010 (
1#
#902
0#
#903
b101011 (
1#
#904
0#
#905
b101100 (
1#
#906
0#
#907
b101101 (
1#
#908
0#
#909
b101110 (
1#
#910
0#
#911
b101111 (
1#
#912
0#
#913
b110000 (
1#
#914
0#
#915
b110001 (
1#
#916
0#
#917
b110010 (
1#
#918
0#
#919
b110011 (
1#
#920
0#
#921
b110100 (
1#
#922
0#
#923
b110101 (
1#
#924
0#
#925
b110110 (
1#
#926
0#
#927
b110111 (
1#
#928
0#
#929
b111000 (
1#
#930
0#
#931
b111001 (
1#
#932
0#
#933
b111010 (
1#
#934
0#
#935
b111011 (
1#
#936
0#
#937
b111100 (
1#
#938
0#
#939
b111101 (
1#
#940
0#
#941
b111110 (
1#
#942
0#
#943
b111111 (
1#
#944
0#
#945
b1000000 (
1#
#946
0#
#947
b1000001 (
1#
#948
0#
#949
b1000010 (
1#
#950
0#
#951
b1000011 (
1#
#952
0#
#953
b1000100 (
1#
#954
0#
#955
b1000101 (
1#
#956
0#
#957
b1000110 (
1#
#958
0#
#959
b1000111 (
1#
#960
0#
#961
b1001000 (
1#
#962
0#
#963
b1001001 (
1#
#964
0#
#965
b1001010 (
1#
#966
0#
#967
b1001011 (
1#
#968
0#
#969
b1001100 (
1#
#970
0#
#971
b1001101 (
1#
#972
0#
#973
b1001110 (
1#
#974
0#
#975
b1001111 (
1#
#976
0#
#977
b1010000 (
1#
#978
0#
#979
b1010001 (
1#
#980
0#
#981
b1010010 (
1#
#982
0#
#983
b1010011 (
1#
#984
0#
#985
b1010100 (
1#
#986
0#
#987
b1010101 (
1#
#988
0#
#989
b1010110 (
1#
#990
0#
#991
b1010111 (
1#
#992
0#
#993
b1011000 (
1#
#994
0#
#995
b1011001 (
1#
#996
0#
#997
b1011010 (
1#
#998
0#
#999
b1011011 (
1#
