designs_n_tb/18_baud_rate_generator/source_files/baud_rate_generator.v
module baud_rate_generator(
    input wire clk,
    input wire rst,
    output wire baud_clk
);

parameter BAUD_RATE = 9600; // Replace with desired baud rate
reg [15:0] counter;

always @(posedge clk or posedge rst) begin
    if (rst)
        counter <= 0;
    else if (counter == BAUD_RATE / 2 - 1)
        counter <= 0;
    else
        counter <= counter + 1;
end

assign baud_clk = counter == (BAUD_RATE / 2 - 1);

endmodule

designs_n_tb/18_baud_rate_generator/testbench_baud_rate_generator.v
`include "baud_rate_generator.v"
module testbench_baud_rate_generator;

reg clk;
reg rst;
wire baud_clk;

// Instantiate the Baud Rate Generator module
baud_rate_generator DUT (
    .clk(clk),
    .rst(rst),
    .baud_clk(baud_clk)
);

// Clock generation for simulation
initial begin
    clk = 0;
    forever #5 clk = ~clk;
end

// Reset generation
initial begin
    rst = 1;
    #10 rst = 0;
    #100 rst = 1;
    #10000 $finish; // End simulation after a while
end

// Monitor the baud_clk signal
always @(posedge clk) begin
    if (baud_clk)
        $display("Baud Clock: %t", $time);
end

initial begin
    $dumpfile("baud.vcd");
    $dumpvars;
end

endmodule

designs_n_tb/18_baud_rate_generator/top_test_bench.v
module top_level_baud_rate_generator_tb;

// Instantiate the Testbench for Baud Rate Generator module
testbench_baud_rate_generator tb();

endmodule

designs_n_tb/18_baud_rate_generator/baud.vcd
$date
	Thu Aug 10 10:53:15 2023
$end
$version
	Icarus Verilog
$end
$timescale
	1s
$end
$scope module top_level_baud_rate_generator_tb $end
$scope module tb $end
$var wire 1 ! baud_clk $end
$var reg 1 " clk $end
$var reg 1 # rst $end
$scope module DUT $end
$var wire 1 " clk $end
$var wire 1 # rst $end
$var wire 1 ! baud_clk $end
$var reg 16 $ counter [15:0] $end
$upscope $end
$upscope $end
$upscope $end
$enddefinitions $end
#0
$dumpvars
b0 $
1#
0"
0!
$end
#5
1"
#10
0"
0#
#15
b1 $
1"
#20
0"
#25
b10 $
1"
#30
0"
#35
b11 $
1"
#40
0"
#45
b100 $
1"
#50
0"
#55
b101 $
1"
#60
0"
#65
b110 $
1"
#70
0"
#75
b111 $
1"
#80
0"
#85
b1000 $
1"
#90
0"
#95
b1001 $
1"
#100
0"
#105
b1010 $
1"
#110
b0 $
0"
1#
